msc/__init__.py
msc-1.1.20.dist-info/METADATA
msc-1.1.20.dist-info/RECORD
msc-1.1.20.dist-info/WHEEL
msc-1.1.20.dist-info/top_level.txt
